px_processor/README.MD
px_processor/__init__.py
px_processor/base.py
px_processor/config/__init__.py
px_processor/config/csv_.py
px_processor/csv/README.MD
px_processor/csv/__init__.py
px_processor/csv/helper.py
px_processor/csv/main.py
px_processor/errors.py
px_processor/json/README.MD
px_processor/json/__init__.py
px_processor/json/main.py
px_processor/py.typed
px_processor/utils.py
px_processor-0.2.4.dist-info/WHEEL
px_processor-0.2.4.dist-info/METADATA
px_processor-0.2.4.dist-info/RECORD
