Metadata-Version: 2.4
Name: px-processor
Version: 0.2.4
Summary: Process and validate JSON and CSV data with ease.
Keywords: json,csv,data,processor,validation,pre-processing,data-processing,data-validation,data-pre-processing,data-processor,json-processor,csv-processor,json-validation,csv-validation,json-pre-processing,csv-pre-processing,json-data-processing,csv-data-processing,json-data-validation,csv-data-validation,json-data-pre-processing,csv-data-pre-processing,json-data-processor,csv-data
Author: pratheesh-prakash
Author-email: pratheesh-prakash <pratheesh.prakash@cognext.ai>
License-Expression: MIT
Classifier: License :: OSI Approved :: MIT License
Classifier: Programming Language :: Python :: 3.10
Classifier: Programming Language :: Python :: 3.11
Classifier: Programming Language :: Python :: 3.12
Classifier: Programming Language :: Python :: 3.13
Classifier: Development Status :: 4 - Beta
Classifier: Operating System :: OS Independent
Classifier: Intended Audience :: Developers
Classifier: Intended Audience :: Information Technology
Classifier: Intended Audience :: Science/Research
Classifier: Topic :: Software Development :: Pre-processors
Classifier: Topic :: Software Development :: Libraries :: Python Modules
Classifier: Topic :: Scientific/Engineering :: Information Analysis
Classifier: Topic :: File Formats :: JSON
Requires-Dist: numba>=0.61.0
Requires-Dist: orjson>=3.10.12
Requires-Dist: polars>=1.32.1
Requires-Dist: pyarrow>=19.0.0
Requires-Dist: pydantic>=2.10.1
Requires-Dist: pydantic-settings>=2.8.1
Requires-Dist: pandas>=2.2.3 ; extra == 'pandas'
Requires-Dist: polars>=1.20.0 ; extra == 'polars'
Maintainer: pratheesh-prakash
Maintainer-email: pratheesh-prakash <pratheesh.prakash@cognext.ai>
Requires-Python: >=3.10.15
Provides-Extra: pandas
Provides-Extra: polars
